README.md
setup.cfg
setup.py
conveyr/__init__.py
conveyr/_version.py
conveyr/conveyr.py
conveyr.egg-info/PKG-INFO
conveyr.egg-info/SOURCES.txt
conveyr.egg-info/dependency_links.txt
conveyr.egg-info/top_level.txt