Metadata-Version: 2.1
Name: conveyr
Version: 1.1.1
Summary: Conveyor pipline handling library for python 3.5 and later
Home-page: https://github.com/megafetis/mediatr_py
Author: Evgeniy Fetisov
Author-email: me@efetisov.ru
License: MIT -or- Apache License 2.0
Keywords: Conveyor,Conveyr,chain handling,Mediator,pipline,behaviors,saga,Chain,pattern builder,async conveyor,architecture pattern
Platform: UNKNOWN
Classifier: Development Status :: 5 - Production/Stable
Classifier: Intended Audience :: Developers
Classifier: Topic :: Software Development :: Build Tools
Classifier: License :: OSI Approved :: MIT License
Classifier: License :: OSI Approved :: Apache Software License
Classifier: Programming Language :: Python :: Implementation :: CPython
Classifier: Programming Language :: Python :: Implementation :: PyPy
Classifier: Programming Language :: Python :: 3 :: Only
Classifier: Programming Language :: Python :: 3.5
Classifier: Programming Language :: Python :: 3.6
Classifier: Programming Language :: Python :: 3.7
Classifier: Programming Language :: Python :: 3.8
Classifier: Programming Language :: Python :: 3.9
Requires-Python: >=3.5
